setup.py
ssl_scanner/__init__.py
ssl_scanner.egg-info/PKG-INFO
ssl_scanner.egg-info/SOURCES.txt
ssl_scanner.egg-info/dependency_links.txt
ssl_scanner.egg-info/not-zip-safe
ssl_scanner.egg-info/top_level.txt