Metadata-Version: 1.0
Name: ssl-scanner
Version: 1.1
Summary: Save it.
Home-page: http://mad.com
Author: Flying Circus
Author-email: hooman@example.com
License: BPUT
Platform: UNKNOWN
